mask_key/__init__.py
mask_key/api.py
mask_key/main.py
mask_key/utils.py
mask_key-0.3.2.dist-info/LICENSE
mask_key-0.3.2.dist-info/METADATA
mask_key-0.3.2.dist-info/WHEEL
mask_key-0.3.2.dist-info/entry_points.txt
mask_key-0.3.2.dist-info/top_level.txt
mask_key-0.3.2.dist-info/RECORD
